[
  {
    "lang": "applescript",
    "path": "day01/src/day01.applescript",
    "encoding": "macintosh"
  },
  {
    "lang": "vala",
    "path": "day02/src/day02.vala"
  },
  {
    "lang": "zig",
    "path": "day03/src/main.zig"
  },
  {
    "lang": "scheme",
    "path": "day04/src/day04.rkt"
  },
  {
    "lang": "clojure",
    "path": "day05/src/day05/core.clj"
  },
  {
    "lang": "cmake",
    "path": "day06/CMakeLists.txt"
  },
  {
    "lang": "perl",
    "path": "day07/src/day07.pl"
  },
  {
    "lang": "scala",
    "path": "day08/app/src/main/scala/day08/App.scala"
  },
  {
    "lang": "haskell",
    "path": "day09/app/Main.hs"
  },
  {
    "lang": "clike",
    "path": "day10/src/day10.c"
  },
  {
    "lang": "elixir",
    "path": "day11/lib/day11.ex"
  },
  {
    "lang": "java",
    "path": "day12/app/src/main/java/dev/fwcd/aoc2022/day12/App.java"
  }
]
